meerk/__init__.py
meerk/caldav/__init__.py
meerk/caldav/davclient.py
meerk/caldav/objects.py
meerk/caldav/elements/__init__.py
meerk/caldav/elements/base.py
meerk/caldav/elements/cdav.py
meerk/caldav/elements/dav.py
meerk/caldav/elements/ical.py
meerk/caldav/lib/__init__.py
meerk/caldav/lib/error.py
meerk/caldav/lib/namespace.py
meerk/caldav/lib/python_utilities.py
meerk/caldav/lib/url.py
meerk/caldav/lib/vcal.py
meerk/calendar/CalDavCalendar.py
meerk/calendar/Calendar.py
meerk/calendar/CompositeCalendar.py
meerk/calendar/IcsCalendar.py
meerk/calendar/IgnoreDisconnectCalendar.py
meerk/calendar/LoggableCalendar.py
meerk/calendar/__init__.py
meerk/intervals/CalEventsIntervals.py
meerk/intervals/InMemoryTimeIntervals.py
meerk/intervals/Intervals.py
meerk/intervals/SimpleCalEventsIntervals.py
meerk/intervals/SimpleIntervals.py
meerk/intervals/TimeIntervals.py
meerk/intervals/__init__.py
meerk/slack/Api.py
meerk/slack/IgnoreDisconnectApi.py
meerk/slack/SimpleApi.py
meerk/slack/__init__.py
meerk/status/CompositeStatus.py
meerk/status/LoggableStatus.py
meerk/status/SlackStatus.py
meerk/status/Status.py
meerk/status/SyncException.py
meerk/status/__init__.py
tests/StaticAnalysisTest.py
tests/__init__.py
tests/intervals/SimpleCalEventsIntervalsTest.py
tests/intervals/SimpleIntervalsTest.py
tests/intervals/__init__.py
meerk-0.3.1.dist-info/LICENSE
meerk-0.3.1.dist-info/METADATA
meerk-0.3.1.dist-info/WHEEL
meerk-0.3.1.dist-info/top_level.txt
meerk-0.3.1.dist-info/RECORD
