Metadata-Version: 2.1
Name: meerk
Version: 0.3.1
Summary: UNKNOWN
Home-page: https://github.com/nikialeksey/meerk
Author: Alexey Niktin
Author-email: nikialeksey@gmail.com
License: MIT
Platform: UNKNOWN
Classifier: License :: OSI Approved :: MIT License
Classifier: Operating System :: MacOS :: MacOS X
Classifier: Operating System :: POSIX
Classifier: Operating System :: POSIX :: BSD
Classifier: Operating System :: POSIX :: Linux
Classifier: Operating System :: Microsoft :: Windows
Classifier: Programming Language :: Python
Classifier: Programming Language :: Python :: 3
Classifier: Programming Language :: Python :: 3.7
Requires-Dist: slackclient (==1.3.0)
Requires-Dist: schedule (==0.5.0)
Requires-Dist: icalendar (==4.0.2)
Requires-Dist: intervaltree (==2.1.0)
Requires-Dist: vobject (==0.9.6.1)
Requires-Dist: lxml (==4.2.5)
Requires-Dist: requests (==2.19.1)
Requires-Dist: six (==1.11.0)
Requires-Dist: pycodestyle (==2.4.0)
Requires-Dist: pylint (==2.1.1)
Requires-Dist: mypy (==0.630)
